{"type":"FeatureCollection","features":[{"type":"Feature","id":"wind-farms-jaisalmer-wind-belt","properties":{"name":"Jaisalmer Wind Farm (Suzlon flagship cluster)","type":"wind_farm","category":"energy","state":"Rajasthan","district":"Jaisalmer","source":"Suzlon disclosures + MNRE","lastUpdated":"2026-07-07","centroid":[71.1,26.9],"labelAnchor":[71.1,26.9],"bbox":[71.1,26.9,71.1,26.9],"geometryQuality":"point","notes":{"facts":["One of India's largest onshore wind farms — over 1000 MW across multiple sub-clusters.","Suzlon's original showcase project — established the Jaisalmer belt as India's wind capital after Muppandal (Tamil Nadu).","Wind class 5-6 with ~8 m/s mean wind speed at 80 m hub height."],"facts_hi":["भारत के सबसे बड़े स्थलीय पवन फार्मों में से एक — कई उप-क्लस्टरों में 1000 MW से अधिक।","Suzlon की मूल प्रदर्शन परियोजना — मुप्पंडल (तमिलनाडु) के बाद जैसलमेर पेटी को भारत की पवन राजधानी बनाया।","80 m हब ऊँचाई पर ~8 m/s औसत पवन गति के साथ पवन वर्ग 5-6।"],"mnemonic":"","significance":"high","confusedWith":[]},"ecology":{"flora":[],"fauna":[],"ecosystem":""},"governance":{"authority":"RVUNL","status":"operational"},"id":"jaisalmer-wind-belt","capacity_mw":1064,"developer":"Suzlon Energy","commissioned":"2001-2013 (multi-phase build-out)","name_hi":"जैसलमेर पवन फार्म (सुज़लॉन प्रमुख क्लस्टर)","commissioned_hi":"2001-2013 (बहु-चरण निर्माण)","district_hi":"जैसलमेर"},"geometry":{"type":"Point","coordinates":[71.1,26.9]}},{"type":"Feature","id":"wind-farms-barmer-wind-zone","properties":{"name":"Barmer Wind Zone","type":"wind_farm","category":"energy","state":"Rajasthan","district":"Barmer","source":"MNRE state-wise wind capacity + operator disclosures","lastUpdated":"2026-07-07","centroid":[71.4,25.9],"labelAnchor":[71.4,25.9],"bbox":[71.4,25.9,71.4,25.9],"geometryQuality":"point","notes":{"facts":["Wind resource contiguous with Jaisalmer — Barmer's belt sits along the Aravalli-perpendicular Thar winds.","Many farms now co-located with solar under hybrid park policy."],"facts_hi":["जैसलमेर से सटा पवन संसाधन — बाड़मेर की पेटी अरावली-लंबवत थार पवनों के साथ है।","अब कई फार्म हाइब्रिड पार्क नीति के तहत सौर के साथ सह-स्थित हैं।"],"mnemonic":"","significance":"high","confusedWith":[]},"ecology":{"flora":[],"fauna":[],"ecosystem":""},"governance":{"authority":"RVUNL","status":"operational"},"id":"barmer-wind-zone","capacity_mw":800,"developer":"Vestas · ReNew · Adani","commissioned":"Multi-phase 2005 onwards","name_hi":"बाड़मेर पवन क्षेत्र","commissioned_hi":"2005 से बहु-चरण","district_hi":"बाड़मेर"},"geometry":{"type":"Point","coordinates":[71.4,25.9]}},{"type":"Feature","id":"wind-farms-jodhpur-wind-cluster","properties":{"name":"Jodhpur Wind Cluster (Osian belt)","type":"wind_farm","category":"energy","state":"Rajasthan","district":"Jodhpur","source":"MNRE + operator disclosures","lastUpdated":"2026-07-07","centroid":[72.9,26.9],"labelAnchor":[72.9,26.9],"bbox":[72.9,26.9,72.9,26.9],"geometryQuality":"point","notes":{"facts":["Osian (Jodhpur) hosts one of the state's earliest Enercon wind clusters.","Wind resource is Class 4-5 (mean 6.5-7.5 m/s at 80 m)."],"facts_hi":["ओसियाँ (जोधपुर) में राज्य के सबसे आरंभिक Enercon पवन क्लस्टरों में से एक है।","पवन संसाधन वर्ग 4-5 (80 m पर औसत 6.5-7.5 m/s)।"],"mnemonic":"","significance":"high","confusedWith":[]},"ecology":{"flora":[],"fauna":[],"ecosystem":""},"governance":{"authority":"RVUNL","status":"operational"},"id":"jodhpur-wind-cluster","capacity_mw":500,"developer":"Enercon (Wobben) · Suzlon","commissioned":"2003 onwards","name_hi":"जोधपुर पवन क्लस्टर (ओसियाँ पेटी)","commissioned_hi":"2003 से","district_hi":"जोधपुर"},"geometry":{"type":"Point","coordinates":[72.9,26.9]}},{"type":"Feature","id":"wind-farms-phalodi-wind-cluster","properties":{"name":"Phalodi Wind Cluster","type":"wind_farm","category":"energy","state":"Rajasthan","district":"Phalodi","source":"MNRE + ReNew disclosures","lastUpdated":"2026-07-07","centroid":[72.35,27.15],"labelAnchor":[72.35,27.15],"bbox":[72.35,27.15,72.35,27.15],"geometryQuality":"point","notes":{"facts":["Newer wind farms clustered around Phalodi and Pokhran — the transition zone between Jaisalmer and Jodhpur wind belts."],"facts_hi":["फलोदी और पोकरण के आसपास नए पवन फार्म — जैसलमेर और जोधपुर पवन पेटियों के बीच संक्रमण क्षेत्र।"],"mnemonic":"","significance":"high","confusedWith":[]},"ecology":{"flora":[],"fauna":[],"ecosystem":""},"governance":{"authority":"RVUNL","status":"operational"},"id":"phalodi-wind-cluster","capacity_mw":400,"developer":"ReNew Power · Adani","commissioned":"2015 onwards","name_hi":"फलोदी पवन क्लस्टर","commissioned_hi":"2015 से","district_hi":"फलोदी"},"geometry":{"type":"Point","coordinates":[72.35,27.15]}}]}