{"type":"FeatureCollection","features":[{"type":"Feature","id":"wind-farms-jaisalmer-wind-belt","properties":{"name":"Jaisalmer Wind Farm (Suzlon flagship cluster)","type":"wind_farm","category":"energy","state":"Rajasthan","district":"Jaisalmer","source":"Suzlon disclosures + MNRE","lastUpdated":"2026-07-07","centroid":[71.1,26.9],"labelAnchor":[71.1,26.9],"bbox":[71.1,26.9,71.1,26.9],"geometryQuality":"point","notes":{"facts":["One of India's largest onshore wind farms \u2014 over 1000 MW across multiple sub-clusters.","Suzlon's original showcase project \u2014 established the Jaisalmer belt as India's wind capital after Muppandal (Tamil Nadu).","Wind class 5-6 with ~8 m/s mean wind speed at 80 m hub height."],"mnemonic":"","significance":"high","confusedWith":[]},"ecology":{"flora":[],"fauna":[],"ecosystem":""},"governance":{"authority":"RVUNL","status":"operational"},"id":"jaisalmer-wind-belt","capacity_mw":1064,"developer":"Suzlon Energy","commissioned":"2001-2013 (multi-phase build-out)"},"geometry":{"type":"Point","coordinates":[71.1,26.9]}},{"type":"Feature","id":"wind-farms-barmer-wind-zone","properties":{"name":"Barmer Wind Zone","type":"wind_farm","category":"energy","state":"Rajasthan","district":"Barmer","source":"MNRE state-wise wind capacity + operator disclosures","lastUpdated":"2026-07-07","centroid":[71.4,25.9],"labelAnchor":[71.4,25.9],"bbox":[71.4,25.9,71.4,25.9],"geometryQuality":"point","notes":{"facts":["Wind resource contiguous with Jaisalmer \u2014 Barmer's belt sits along the Aravalli-perpendicular Thar winds.","Many farms now co-located with solar under hybrid park policy."],"mnemonic":"","significance":"high","confusedWith":[]},"ecology":{"flora":[],"fauna":[],"ecosystem":""},"governance":{"authority":"RVUNL","status":"operational"},"id":"barmer-wind-zone","capacity_mw":800,"developer":"Vestas \u00b7 ReNew \u00b7 Adani","commissioned":"Multi-phase 2005 onwards"},"geometry":{"type":"Point","coordinates":[71.4,25.9]}},{"type":"Feature","id":"wind-farms-jodhpur-wind-cluster","properties":{"name":"Jodhpur Wind Cluster (Osian belt)","type":"wind_farm","category":"energy","state":"Rajasthan","district":"Jodhpur","source":"MNRE + operator disclosures","lastUpdated":"2026-07-07","centroid":[72.9,26.9],"labelAnchor":[72.9,26.9],"bbox":[72.9,26.9,72.9,26.9],"geometryQuality":"point","notes":{"facts":["Osian (Jodhpur) hosts one of the state's earliest Enercon wind clusters.","Wind resource is Class 4-5 (mean 6.5-7.5 m/s at 80 m)."],"mnemonic":"","significance":"high","confusedWith":[]},"ecology":{"flora":[],"fauna":[],"ecosystem":""},"governance":{"authority":"RVUNL","status":"operational"},"id":"jodhpur-wind-cluster","capacity_mw":500,"developer":"Enercon (Wobben) \u00b7 Suzlon","commissioned":"2003 onwards"},"geometry":{"type":"Point","coordinates":[72.9,26.9]}},{"type":"Feature","id":"wind-farms-phalodi-wind-cluster","properties":{"name":"Phalodi Wind Cluster","type":"wind_farm","category":"energy","state":"Rajasthan","district":"Phalodi","source":"MNRE + ReNew disclosures","lastUpdated":"2026-07-07","centroid":[72.35,27.15],"labelAnchor":[72.35,27.15],"bbox":[72.35,27.15,72.35,27.15],"geometryQuality":"point","notes":{"facts":["Newer wind farms clustered around Phalodi and Pokhran \u2014 the transition zone between Jaisalmer and Jodhpur wind belts."],"mnemonic":"","significance":"high","confusedWith":[]},"ecology":{"flora":[],"fauna":[],"ecosystem":""},"governance":{"authority":"RVUNL","status":"operational"},"id":"phalodi-wind-cluster","capacity_mw":400,"developer":"ReNew Power \u00b7 Adani","commissioned":"2015 onwards"},"geometry":{"type":"Point","coordinates":[72.35,27.15]}}]}